daybetter_local_api/__init__.py
daybetter_local_api/controller.py
daybetter_local_api/device.py
daybetter_local_api/device_registry.py
daybetter_local_api/light_capabilities.py
daybetter_local_api/message.py
daybetter_local_api-1.0.7.dist-info/licenses/LICENSE
daybetter_local_api-1.0.7.dist-info/METADATA
daybetter_local_api-1.0.7.dist-info/WHEEL
daybetter_local_api-1.0.7.dist-info/RECORD
