Metadata-Version: 2.4
Name: daybetter-local-api
Version: 1.0.7
Summary: Library to communicate with daybetter local API
License-Expression: Apache-2.0
License-File: LICENSE
Author: DayBetter
Author-email: moyuliu39@gmail.com
Requires-Python: >=3.11
Classifier: Development Status :: 2 - Pre-Alpha
Classifier: Intended Audience :: Developers
Classifier: Natural Language :: English
Classifier: Operating System :: OS Independent
Classifier: Programming Language :: Python :: 3
Classifier: Programming Language :: Python :: 3.11
Classifier: Programming Language :: Python :: 3.12
Classifier: Programming Language :: Python :: 3.13
Classifier: Programming Language :: Python :: 3.14
Classifier: Topic :: Software Development :: Libraries
Project-URL: Bug Tracker, https://github.com/DayBetter/daybetter-local-api/issues
Project-URL: Repository, https://github.com/DayBetter/daybetter-local-api
